{
    "title": "AZ-305 Practice Section 1",
    "description": "Azure Solutions Architect Expert (AZ-305) - 36 Practice Questions (12 case study-linked + 24 standalone)",
    "slug": "az-305-practice-section-1",
    "category": "Azure Certification",
    "preview_image": "assets/images/preview_az305.svg",
    "questions": [
        "questions/01-zenith-oauth.json",
        "questions/02-zenith-token.json",
        "questions/03-zenith-db.json",
        "questions/04-stratos-app.json",
        "questions/05-stratos-db.json",
        "questions/06-stratos-identity.json",
        "questions/07-alta-perm.json",
        "questions/08-alta-jwt.json",
        "questions/09-alta-gov.json",
        "questions/10-chrono-policy.json",
        "questions/11-chrono-alert.json",
        "questions/12-chrono-blob.json",
        "questions/13-zenith-report.json",
        "questions/14-zenith-kv.json",
        "questions/15-zenith-ident.json",
        "questions/16-stratos-sql.json",
        "questions/17-stratos-files.json",
        "questions/18-stratos-events.json",
        "questions/19-stratos-priv.json",
        "questions/20-stratos-tier.json",
        "questions/21-alta-match.json",
        "questions/22-chrono-logs.json",
        "questions/23-chrono-trans.json",
        "questions/24-chrono-agent.json",
        "questions/25-network-hub-spoke.json",
        "questions/26-compute-aks-design.json",
        "questions/27-bcdr-geo-replication.json",
        "questions/28-app-apim-policy.json",
        "questions/29-data-cosmos-partition.json",
        "questions/30-security-keyvault-design.json",
        "questions/31-app-messaging-design.json",
        "questions/32-compute-app-service-plan.json",
        "questions/33-bcdr-backup-strategy.json",
        "questions/34-network-private-link.json",
        "questions/35-migration-strategy.json",
        "questions/36-data-storage-tier.json"
    ]
}